terra_byte/README.md
terra_byte/__init__.py
terra_byte/model/__init__.py
terra_byte/model/flash_triton.py
terra_byte/model/helpers.py
terra_byte/model/megabyte.py
terra_byte/model/model.py
terra_byte/model/multimodal_preprocessor.py
terra_byte/model/omnibyte.py
terra_byte/model/patches.py
terra_byte/model/transformer.py
terra_byte/terrabyte.py
terra_byte/training/__init__.py
terra_byte/training/train.py
terra_byte/utils/__init__.py
terra_byte/utils/stable_adamw.py
terrabyte-0.1.6.dist-info/LICENSE
terrabyte-0.1.6.dist-info/WHEEL
terrabyte-0.1.6.dist-info/METADATA
terrabyte-0.1.6.dist-info/RECORD
