Metadata-Version: 2.1
Name: terrabyte
Version: 0.1.6
Summary: TerraByte - Pytorch
License: MIT
Author: Kye Gomez
Author-email: kye@apac.ai
Requires-Python: >=3.6,<4.0
Classifier: License :: OSI Approved :: MIT License
Classifier: Programming Language :: Python :: 3
Classifier: Programming Language :: Python :: 3.6
Classifier: Programming Language :: Python :: 3.7
Classifier: Programming Language :: Python :: 3.8
Classifier: Programming Language :: Python :: 3.9
Classifier: Programming Language :: Python :: 3.10
Classifier: Programming Language :: Python :: 3.11
Requires-Dist: beartype (>=0.8.1,<0.9.0)
Requires-Dist: einops (>=0.3.0,<0.4.0)
Requires-Dist: torch (>=1.9.0,<2.0.0)
Requires-Dist: triton (>=1.0.0,<2.0.0)
